Metadata-Version: 2.1
Name: SegmentCar
Version: 0.1.2
Requires-Dist: numpy
Requires-Dist: tensorflow
Requires-Dist: ultralytics
Requires-Dist: segment-anything
Requires-Dist: tqdm
Requires-Dist: requests
